ersatz_table_valued_functions/__init__.py
ersatz_table_valued_functions-0.2.dist-info/LICENSE
ersatz_table_valued_functions-0.2.dist-info/METADATA
ersatz_table_valued_functions-0.2.dist-info/WHEEL
ersatz_table_valued_functions-0.2.dist-info/top_level.txt
ersatz_table_valued_functions-0.2.dist-info/RECORD
