Metadata-Version: 2.1
Name: ersatz-table-valued-functions
Version: 0.2
Summary: A bad idea.
Home-page: https://github.com/cldellow/ersatz-table-valued-functions
Author: Colin Dellow
License: Apache License, Version 2.0
Project-URL: Issues, https://github.com/cldellow/ersatz-table-valued-functions/issues
Project-URL: CI, https://github.com/cldellow/ersatz-table-valued-functions/actions
Project-URL: Changelog, https://github.com/cldellow/ersatz-table-valued-functions/releases
Requires-Python: >=3.7
License-File: LICENSE
Requires-Dist: sqlglot
Provides-Extra: test
Requires-Dist: pytest ; extra == 'test'
Requires-Dist: pytest-watch ; extra == 'test'
